./.gitignore
./PKG-INFO
./README.md
./pyproject.toml
./test_testmark.py
./testmark.py
testmark_pytest-0.0.2.dist-info/METADATA
testmark_pytest-0.0.2.dist-info/WHEEL
testmark_pytest-0.0.2.dist-info/RECORD
