Metadata-Version: 2.4
Name: testmark-pytest
Version: 0.0.2
Summary: Write language-agnostic unit tests in Markdown. Run them in pytest.
Project-URL: Repository, https://github.com/holdenmatt/testmark
Author: Matt Holden
License: MIT
Requires-Python: >=3.8
